pullnrun/__init__.py
pullnrun/__main__.py
pullnrun/_version.py
pullnrun/execute.py
pullnrun/main.py
pullnrun/validate.py
pullnrun/builtin/__init__.py
pullnrun/builtin/_misc.py
pullnrun/builtin/_pull.py
pullnrun/builtin/_push.py
pullnrun/builtin/_run.py
pullnrun/schemas/__init__.py
pullnrun/schemas/console.yml
pullnrun/schemas/plan.yml
pullnrun/templates/__init__.py
pullnrun/templates/report.html.j2
pullnrun/utils/__init__.py
pullnrun/utils/console.py
pullnrun/utils/data.py
pullnrun/utils/task.py
pullnrun/utils/template.py
pullnrun-0.8.0.data/scripts/pullnrun
pullnrun-0.8.0.dist-info/LICENSE
pullnrun-0.8.0.dist-info/METADATA
pullnrun-0.8.0.dist-info/WHEEL
pullnrun-0.8.0.dist-info/top_level.txt
pullnrun-0.8.0.dist-info/RECORD
