Metadata-Version: 2.1
Name: pullnrun
Version: 0.8.0
Summary: A simple python app for running a set of commands from remote sources and pushing result files to remote targets.
Home-page: https://github.com/kangasta/pullnrun
Author: Toni Kangas
License: UNKNOWN
Platform: UNKNOWN
Classifier: Programming Language :: Python :: 3
Classifier: License :: OSI Approved :: MIT License
Classifier: Operating System :: OS Independent
Requires-Dist: Jinja2 (~=2.0)
Requires-Dist: jsonschema (~=3.0)
Requires-Dist: pyyaml (~=5.0)
Requires-Dist: requests (~=2.0)
Requires-Dist: importlib-resources ; python_version < "3.7"
